taxontabletools/CCA_analysis.py
taxontabletools/NMDS_analysis.py
taxontabletools/PCoA_analysis.py
taxontabletools/__init__.py
taxontabletools/__main__.py
taxontabletools/alpha_diversity.py
taxontabletools/basic_stats.py
taxontabletools/beta_diversity.py
taxontabletools/calculate_taxonomic_resolution.py
taxontabletools/calculate_taxonomic_richness.py
taxontabletools/check_read_table_format.py
taxontabletools/check_taXon_table_format.py
taxontabletools/check_taxononomy_table_format.py
taxontabletools/combine_replicates.py
taxontabletools/convert_to_perlodes.py
taxontabletools/convert_to_presence_absence.py
taxontabletools/create_krona_chart.py
taxontabletools/create_log.py
taxontabletools/create_metadata_table.py
taxontabletools/create_taxon_list.py
taxontabletools/create_taxon_table_per_sample.py
taxontabletools/gbif_check_taxonomy.py
taxontabletools/gbif_occurrence.py
taxontabletools/get_available_meta_data.py
taxontabletools/parcat_analysis.py
taxontabletools/per_taxon_analysis.py
taxontabletools/rarefaction_curve.py
taxontabletools/read_proportions.py
taxontabletools/replicate_analysis.py
taxontabletools/replicate_consistency_filter.py
taxontabletools/replicate_correlation_analysis.py
taxontabletools/site_occupancy.py
taxontabletools/taxon_table_converter.py
taxontabletools/taxon_table_filtering.py
taxontabletools/user_data.txt
taxontabletools/venn_diagram.py
taxontabletools/_source/crash.png
taxontabletools/_source/fliessgewaesserbewertung_de.png
taxontabletools/_source/github.png
taxontabletools/_source/main.png
taxontabletools/_source/taxontabletools.png
taxontabletools/_source/twitter.png
taxontabletools-1.3.0.dist-info/LICENSE
taxontabletools-1.3.0.dist-info/METADATA
taxontabletools-1.3.0.dist-info/WHEEL
taxontabletools-1.3.0.dist-info/top_level.txt
taxontabletools-1.3.0.dist-info/RECORD
