Metadata-Version: 2.1
Name: taxontabletools
Version: 1.3.0
Summary: TaxonTableTools - A comprehensive, platform-independent graphical user interface software to explore and visualise DNA metabarcoding data
Home-page: https://github.com/pypa/taxontabletools
Author: Till-Hendrik Macher
Author-email: till-hendrik.macher@uni-due.de
License: MIT
Platform: UNKNOWN
Classifier: Programming Language :: Python :: 3
Classifier: License :: OSI Approved :: MIT License
Classifier: Operating System :: OS Independent
Requires-Python: >=3.6
Requires-Dist: pySimpleGUI (>=4.15.2)
Requires-Dist: pandas (>=0.25.3)
Requires-Dist: numpy (>=1.18.1)
Requires-Dist: matplotlib-venn (>=0.11.5)
Requires-Dist: xlrd (>=1.2.0)
Requires-Dist: openpyxl (>=3.0.3)
Requires-Dist: xlsxwriter (>=1.2.7)
Requires-Dist: biopython (>=1.77)
Requires-Dist: scikit-bio (>=0.5.6)
Requires-Dist: requests-html (>=0.10.0)
Requires-Dist: scipy (>=1.5.1)
Requires-Dist: shapely (>=1.7.1)
Requires-Dist: plotly (>=4.9.0)
Requires-Dist: kaleido (>=0.0.3)
Requires-Dist: statsmodels (>=0.12.1)
Requires-Dist: lastversion (>=1.3.3)
Requires-Dist: networkx (>=2.4)
